maxar_ard_grid/__init__.py
maxar_ard_grid/grid.py
maxar_ard_grid-1.2.2.dist-info/LICENSE
maxar_ard_grid-1.2.2.dist-info/WHEEL
maxar_ard_grid-1.2.2.dist-info/METADATA
maxar_ard_grid-1.2.2.dist-info/RECORD
