Metadata-Version: 2.1
Name: maxar-ard-grid
Version: 1.2.2
Summary: Tools for the Maxar ARD grid
License: MIT
Author: Marc Pfister
Author-email: marc.pfister@maxar.com
Requires-Python: >=3.8,<4.0
Classifier: License :: OSI Approved :: MIT License
Classifier: Programming Language :: Python :: 3
Classifier: Programming Language :: Python :: 3.10
Classifier: Programming Language :: Python :: 3.8
Classifier: Programming Language :: Python :: 3.9
Requires-Dist: Shapely (>=1.6.4)
Requires-Dist: pyproj (>=3.4.0)
Project-URL: Documentation, https://ard.maxar.com/docs/sdk/sdk/grid/
